texgen.py
texgenredvin-0.1.0.dist-info/METADATA
texgenredvin-0.1.0.dist-info/WHEEL
texgenredvin-0.1.0.dist-info/top_level.txt
texgenredvin-0.1.0.dist-info/RECORD
