Metadata-Version: 2.2
Name: texgenRedvin
Version: 0.1.0
Summary: Study package
Author-email: Redvin <pakman12344321@mail.ru>
License: MIT License
Project-URL: Homepage, https://github.com/Redvin-dt/PythonAdvancedHW/tree/hw2/hw_2/library
Keywords: texgen
Classifier: License :: OSI Approved :: MIT License
Classifier: Programming Language :: Python
Classifier: Programming Language :: Python :: 3
Requires-Python: >=3.12
